{
  "user" :{
    "id": "abc123",
    "name": "김철수",
    "age": 22,
    "address": "강남구 역삼동",
    "gender": "M"
  },
  "users":[
    {
      "id": "aaa",
      "email": "aaa@naver.com",
      "name": "김철수",
      "age": 22,
      "address": "강남구 역삼동",
      "gender": "M"
    },
    {
      "id": "bbb",
      "email": "bbb@naver.com",
      "name": "김영희",
      "age": 24,
      "address": "성북구 보문동",
      "gender": "F"
    },
    {
      "id": "ccc",
      "email": "ccc@naver.com",
      "name": "박웅이",
      "age": 11,
      "address": "성북구 삼선동",
      "gender": "M"
    },
    {
      "id": "ddd",
      "email": "ddd@naver.com",
      "name": "이유리",
      "age": 20,
      "address": "강남구 논현동",
      "gender": "F"
    }
  ]
}
